{
    "RunTime": 24.751213625,
    "tests": {
        "0": {
            "MessageAdversaryPower": 0,
            "avgDeliveryNodes": 100.0,
            "avgDeliveryTime": 5.731958762886598,
            "byzantineNodes": [
                59,
                70,
                78
            ],
            "disconnectedNodes": [],
            "maxDeliveryTime": 6,
            "senderId": 0,
            "totalMsgsSent": 171210
        },
        "1": {
            "MessageAdversaryPower": 0,
            "avgDeliveryNodes": 100.0,
            "avgDeliveryTime": 5.731958762886598,
            "byzantineNodes": [
                59,
                70,
                78
            ],
            "disconnectedNodes": [],
            "maxDeliveryTime": 6,
            "senderId": 0,
            "totalMsgsSent": 171210
        },
        "10": {
            "MessageAdversaryPower": 0,
            "avgDeliveryNodes": 100.0,
            "avgDeliveryTime": 5.731958762886598,
            "byzantineNodes": [
                59,
                70,
                78
            ],
            "disconnectedNodes": [],
            "maxDeliveryTime": 6,
            "senderId": 0,
            "totalMsgsSent": 171210
        },
        "11": {
            "MessageAdversaryPower": 0,
            "avgDeliveryNodes": 100.0,
            "avgDeliveryTime": 5.731958762886598,
            "byzantineNodes": [
                59,
                70,
                78
            ],
            "disconnectedNodes": [],
            "maxDeliveryTime": 6,
            "senderId": 0,
            "totalMsgsSent": 171210
        },
        "12": {
            "MessageAdversaryPower": 0,
            "avgDeliveryNodes": 100.0,
            "avgDeliveryTime": 5.731958762886598,
            "byzantineNodes": [
                59,
                70,
                78
            ],
            "disconnectedNodes": [],
            "maxDeliveryTime": 6,
            "senderId": 0,
            "totalMsgsSent": 171210
        },
        "13": {
            "MessageAdversaryPower": 0,
            "avgDeliveryNodes": 100.0,
            "avgDeliveryTime": 5.731958762886598,
            "byzantineNodes": [
                59,
                70,
                78
            ],
            "disconnectedNodes": [],
            "maxDeliveryTime": 6,
            "senderId": 0,
            "totalMsgsSent": 171210
        },
        "14": {
            "MessageAdversaryPower": 0,
            "avgDeliveryNodes": 100.0,
            "avgDeliveryTime": 5.731958762886598,
            "byzantineNodes": [
                59,
                70,
                78
            ],
            "disconnectedNodes": [],
            "maxDeliveryTime": 6,
            "senderId": 0,
            "totalMsgsSent": 171210
        },
        "15": {
            "MessageAdversaryPower": 0,
            "avgDeliveryNodes": 100.0,
            "avgDeliveryTime": 5.731958762886598,
            "byzantineNodes": [
                59,
                70,
                78
            ],
            "disconnectedNodes": [],
            "maxDeliveryTime": 6,
            "senderId": 0,
            "totalMsgsSent": 171210
        },
        "16": {
            "MessageAdversaryPower": 0,
            "avgDeliveryNodes": 100.0,
            "avgDeliveryTime": 5.731958762886598,
            "byzantineNodes": [
                59,
                70,
                78
            ],
            "disconnectedNodes": [],
            "maxDeliveryTime": 6,
            "senderId": 0,
            "totalMsgsSent": 171210
        },
        "17": {
            "MessageAdversaryPower": 0,
            "avgDeliveryNodes": 100.0,
            "avgDeliveryTime": 5.731958762886598,
            "byzantineNodes": [
                59,
                70,
                78
            ],
            "disconnectedNodes": [],
            "maxDeliveryTime": 6,
            "senderId": 0,
            "totalMsgsSent": 171210
        },
        "18": {
            "MessageAdversaryPower": 0,
            "avgDeliveryNodes": 100.0,
            "avgDeliveryTime": 5.731958762886598,
            "byzantineNodes": [
                59,
                70,
                78
            ],
            "disconnectedNodes": [],
            "maxDeliveryTime": 6,
            "senderId": 0,
            "totalMsgsSent": 171210
        },
        "19": {
            "MessageAdversaryPower": 0,
            "avgDeliveryNodes": 100.0,
            "avgDeliveryTime": 5.731958762886598,
            "byzantineNodes": [
                59,
                70,
                78
            ],
            "disconnectedNodes": [],
            "maxDeliveryTime": 6,
            "senderId": 0,
            "totalMsgsSent": 171210
        },
        "2": {
            "MessageAdversaryPower": 0,
            "avgDeliveryNodes": 100.0,
            "avgDeliveryTime": 5.731958762886598,
            "byzantineNodes": [
                59,
                70,
                78
            ],
            "disconnectedNodes": [],
            "maxDeliveryTime": 6,
            "senderId": 0,
            "totalMsgsSent": 171210
        },
        "20": {
            "MessageAdversaryPower": 0,
            "avgDeliveryNodes": 100.0,
            "avgDeliveryTime": 5.731958762886598,
            "byzantineNodes": [
                59,
                70,
                78
            ],
            "disconnectedNodes": [],
            "maxDeliveryTime": 6,
            "senderId": 0,
            "totalMsgsSent": 171210
        },
        "21": {
            "MessageAdversaryPower": 0,
            "avgDeliveryNodes": 100.0,
            "avgDeliveryTime": 5.731958762886598,
            "byzantineNodes": [
                59,
                70,
                78
            ],
            "disconnectedNodes": [],
            "maxDeliveryTime": 6,
            "senderId": 0,
            "totalMsgsSent": 171210
        },
        "22": {
            "MessageAdversaryPower": 0,
            "avgDeliveryNodes": 100.0,
            "avgDeliveryTime": 5.731958762886598,
            "byzantineNodes": [
                59,
                70,
                78
            ],
            "disconnectedNodes": [],
            "maxDeliveryTime": 6,
            "senderId": 0,
            "totalMsgsSent": 171210
        },
        "23": {
            "MessageAdversaryPower": 0,
            "avgDeliveryNodes": 100.0,
            "avgDeliveryTime": 5.731958762886598,
            "byzantineNodes": [
                59,
                70,
                78
            ],
            "disconnectedNodes": [],
            "maxDeliveryTime": 6,
            "senderId": 0,
            "totalMsgsSent": 171210
        },
        "24": {
            "MessageAdversaryPower": 0,
            "avgDeliveryNodes": 100.0,
            "avgDeliveryTime": 5.731958762886598,
            "byzantineNodes": [
                59,
                70,
                78
            ],
            "disconnectedNodes": [],
            "maxDeliveryTime": 6,
            "senderId": 0,
            "totalMsgsSent": 171210
        },
        "25": {
            "MessageAdversaryPower": 0,
            "avgDeliveryNodes": 100.0,
            "avgDeliveryTime": 5.731958762886598,
            "byzantineNodes": [
                59,
                70,
                78
            ],
            "disconnectedNodes": [],
            "maxDeliveryTime": 6,
            "senderId": 0,
            "totalMsgsSent": 171210
        },
        "26": {
            "MessageAdversaryPower": 0,
            "avgDeliveryNodes": 100.0,
            "avgDeliveryTime": 5.731958762886598,
            "byzantineNodes": [
                59,
                70,
                78
            ],
            "disconnectedNodes": [],
            "maxDeliveryTime": 6,
            "senderId": 0,
            "totalMsgsSent": 171210
        },
        "27": {
            "MessageAdversaryPower": 0,
            "avgDeliveryNodes": 100.0,
            "avgDeliveryTime": 5.731958762886598,
            "byzantineNodes": [
                59,
                70,
                78
            ],
            "disconnectedNodes": [],
            "maxDeliveryTime": 6,
            "senderId": 0,
            "totalMsgsSent": 171210
        },
        "28": {
            "MessageAdversaryPower": 0,
            "avgDeliveryNodes": 100.0,
            "avgDeliveryTime": 5.731958762886598,
            "byzantineNodes": [
                59,
                70,
                78
            ],
            "disconnectedNodes": [],
            "maxDeliveryTime": 6,
            "senderId": 0,
            "totalMsgsSent": 171210
        },
        "29": {
            "MessageAdversaryPower": 0,
            "avgDeliveryNodes": 100.0,
            "avgDeliveryTime": 5.731958762886598,
            "byzantineNodes": [
                59,
                70,
                78
            ],
            "disconnectedNodes": [],
            "maxDeliveryTime": 6,
            "senderId": 0,
            "totalMsgsSent": 171210
        },
        "3": {
            "MessageAdversaryPower": 0,
            "avgDeliveryNodes": 100.0,
            "avgDeliveryTime": 5.731958762886598,
            "byzantineNodes": [
                59,
                70,
                78
            ],
            "disconnectedNodes": [],
            "maxDeliveryTime": 6,
            "senderId": 0,
            "totalMsgsSent": 171210
        },
        "30": {
            "MessageAdversaryPower": 0,
            "avgDeliveryNodes": 100.0,
            "avgDeliveryTime": 5.731958762886598,
            "byzantineNodes": [
                59,
                70,
                78
            ],
            "disconnectedNodes": [],
            "maxDeliveryTime": 6,
            "senderId": 0,
            "totalMsgsSent": 171210
        },
        "31": {
            "MessageAdversaryPower": 0,
            "avgDeliveryNodes": 100.0,
            "avgDeliveryTime": 5.731958762886598,
            "byzantineNodes": [
                59,
                70,
                78
            ],
            "disconnectedNodes": [],
            "maxDeliveryTime": 6,
            "senderId": 0,
            "totalMsgsSent": 171210
        },
        "32": {
            "MessageAdversaryPower": 0,
            "avgDeliveryNodes": 100.0,
            "avgDeliveryTime": 5.731958762886598,
            "byzantineNodes": [
                59,
                70,
                78
            ],
            "disconnectedNodes": [],
            "maxDeliveryTime": 6,
            "senderId": 0,
            "totalMsgsSent": 171210
        },
        "33": {
            "MessageAdversaryPower": 0,
            "avgDeliveryNodes": 100.0,
            "avgDeliveryTime": 5.731958762886598,
            "byzantineNodes": [
                59,
                70,
                78
            ],
            "disconnectedNodes": [],
            "maxDeliveryTime": 6,
            "senderId": 0,
            "totalMsgsSent": 171210
        },
        "34": {
            "MessageAdversaryPower": 0,
            "avgDeliveryNodes": 100.0,
            "avgDeliveryTime": 5.731958762886598,
            "byzantineNodes": [
                59,
                70,
                78
            ],
            "disconnectedNodes": [],
            "maxDeliveryTime": 6,
            "senderId": 0,
            "totalMsgsSent": 171210
        },
        "35": {
            "MessageAdversaryPower": 0,
            "avgDeliveryNodes": 100.0,
            "avgDeliveryTime": 5.731958762886598,
            "byzantineNodes": [
                59,
                70,
                78
            ],
            "disconnectedNodes": [],
            "maxDeliveryTime": 6,
            "senderId": 0,
            "totalMsgsSent": 171210
        },
        "36": {
            "MessageAdversaryPower": 0,
            "avgDeliveryNodes": 100.0,
            "avgDeliveryTime": 5.731958762886598,
            "byzantineNodes": [
                59,
                70,
                78
            ],
            "disconnectedNodes": [],
            "maxDeliveryTime": 6,
            "senderId": 0,
            "totalMsgsSent": 171210
        },
        "37": {
            "MessageAdversaryPower": 0,
            "avgDeliveryNodes": 100.0,
            "avgDeliveryTime": 5.731958762886598,
            "byzantineNodes": [
                59,
                70,
                78
            ],
            "disconnectedNodes": [],
            "maxDeliveryTime": 6,
            "senderId": 0,
            "totalMsgsSent": 171210
        },
        "38": {
            "MessageAdversaryPower": 0,
            "avgDeliveryNodes": 100.0,
            "avgDeliveryTime": 5.731958762886598,
            "byzantineNodes": [
                59,
                70,
                78
            ],
            "disconnectedNodes": [],
            "maxDeliveryTime": 6,
            "senderId": 0,
            "totalMsgsSent": 171210
        },
        "39": {
            "MessageAdversaryPower": 0,
            "avgDeliveryNodes": 100.0,
            "avgDeliveryTime": 5.731958762886598,
            "byzantineNodes": [
                59,
                70,
                78
            ],
            "disconnectedNodes": [],
            "maxDeliveryTime": 6,
            "senderId": 0,
            "totalMsgsSent": 171210
        },
        "4": {
            "MessageAdversaryPower": 0,
            "avgDeliveryNodes": 100.0,
            "avgDeliveryTime": 5.731958762886598,
            "byzantineNodes": [
                59,
                70,
                78
            ],
            "disconnectedNodes": [],
            "maxDeliveryTime": 6,
            "senderId": 0,
            "totalMsgsSent": 171210
        },
        "40": {
            "MessageAdversaryPower": 0,
            "avgDeliveryNodes": 100.0,
            "avgDeliveryTime": 5.731958762886598,
            "byzantineNodes": [
                59,
                70,
                78
            ],
            "disconnectedNodes": [],
            "maxDeliveryTime": 6,
            "senderId": 0,
            "totalMsgsSent": 171210
        },
        "41": {
            "MessageAdversaryPower": 0,
            "avgDeliveryNodes": 100.0,
            "avgDeliveryTime": 5.731958762886598,
            "byzantineNodes": [
                59,
                70,
                78
            ],
            "disconnectedNodes": [],
            "maxDeliveryTime": 6,
            "senderId": 0,
            "totalMsgsSent": 171210
        },
        "42": {
            "MessageAdversaryPower": 0,
            "avgDeliveryNodes": 100.0,
            "avgDeliveryTime": 5.731958762886598,
            "byzantineNodes": [
                59,
                70,
                78
            ],
            "disconnectedNodes": [],
            "maxDeliveryTime": 6,
            "senderId": 0,
            "totalMsgsSent": 171210
        },
        "43": {
            "MessageAdversaryPower": 0,
            "avgDeliveryNodes": 100.0,
            "avgDeliveryTime": 5.731958762886598,
            "byzantineNodes": [
                59,
                70,
                78
            ],
            "disconnectedNodes": [],
            "maxDeliveryTime": 6,
            "senderId": 0,
            "totalMsgsSent": 171210
        },
        "44": {
            "MessageAdversaryPower": 0,
            "avgDeliveryNodes": 100.0,
            "avgDeliveryTime": 5.731958762886598,
            "byzantineNodes": [
                59,
                70,
                78
            ],
            "disconnectedNodes": [],
            "maxDeliveryTime": 6,
            "senderId": 0,
            "totalMsgsSent": 171210
        },
        "45": {
            "MessageAdversaryPower": 0,
            "avgDeliveryNodes": 100.0,
            "avgDeliveryTime": 5.731958762886598,
            "byzantineNodes": [
                59,
                70,
                78
            ],
            "disconnectedNodes": [],
            "maxDeliveryTime": 6,
            "senderId": 0,
            "totalMsgsSent": 171210
        },
        "46": {
            "MessageAdversaryPower": 0,
            "avgDeliveryNodes": 100.0,
            "avgDeliveryTime": 5.731958762886598,
            "byzantineNodes": [
                59,
                70,
                78
            ],
            "disconnectedNodes": [],
            "maxDeliveryTime": 6,
            "senderId": 0,
            "totalMsgsSent": 171210
        },
        "47": {
            "MessageAdversaryPower": 0,
            "avgDeliveryNodes": 100.0,
            "avgDeliveryTime": 5.731958762886598,
            "byzantineNodes": [
                59,
                70,
                78
            ],
            "disconnectedNodes": [],
            "maxDeliveryTime": 6,
            "senderId": 0,
            "totalMsgsSent": 171210
        },
        "48": {
            "MessageAdversaryPower": 0,
            "avgDeliveryNodes": 100.0,
            "avgDeliveryTime": 5.731958762886598,
            "byzantineNodes": [
                59,
                70,
                78
            ],
            "disconnectedNodes": [],
            "maxDeliveryTime": 6,
            "senderId": 0,
            "totalMsgsSent": 171210
        },
        "49": {
            "MessageAdversaryPower": 0,
            "avgDeliveryNodes": 100.0,
            "avgDeliveryTime": 5.731958762886598,
            "byzantineNodes": [
                59,
                70,
                78
            ],
            "disconnectedNodes": [],
            "maxDeliveryTime": 6,
            "senderId": 0,
            "totalMsgsSent": 171210
        },
        "5": {
            "MessageAdversaryPower": 0,
            "avgDeliveryNodes": 100.0,
            "avgDeliveryTime": 5.731958762886598,
            "byzantineNodes": [
                59,
                70,
                78
            ],
            "disconnectedNodes": [],
            "maxDeliveryTime": 6,
            "senderId": 0,
            "totalMsgsSent": 171210
        },
        "50": {
            "MessageAdversaryPower": 0,
            "avgDeliveryNodes": 100.0,
            "avgDeliveryTime": 5.731958762886598,
            "byzantineNodes": [
                59,
                70,
                78
            ],
            "disconnectedNodes": [],
            "maxDeliveryTime": 6,
            "senderId": 0,
            "totalMsgsSent": 171210
        },
        "51": {
            "MessageAdversaryPower": 0,
            "avgDeliveryNodes": 100.0,
            "avgDeliveryTime": 5.731958762886598,
            "byzantineNodes": [
                59,
                70,
                78
            ],
            "disconnectedNodes": [],
            "maxDeliveryTime": 6,
            "senderId": 0,
            "totalMsgsSent": 171210
        },
        "52": {
            "MessageAdversaryPower": 0,
            "avgDeliveryNodes": 100.0,
            "avgDeliveryTime": 5.731958762886598,
            "byzantineNodes": [
                59,
                70,
                78
            ],
            "disconnectedNodes": [],
            "maxDeliveryTime": 6,
            "senderId": 0,
            "totalMsgsSent": 171210
        },
        "53": {
            "MessageAdversaryPower": 0,
            "avgDeliveryNodes": 100.0,
            "avgDeliveryTime": 5.731958762886598,
            "byzantineNodes": [
                59,
                70,
                78
            ],
            "disconnectedNodes": [],
            "maxDeliveryTime": 6,
            "senderId": 0,
            "totalMsgsSent": 171210
        },
        "54": {
            "MessageAdversaryPower": 0,
            "avgDeliveryNodes": 100.0,
            "avgDeliveryTime": 5.731958762886598,
            "byzantineNodes": [
                59,
                70,
                78
            ],
            "disconnectedNodes": [],
            "maxDeliveryTime": 6,
            "senderId": 0,
            "totalMsgsSent": 171210
        },
        "55": {
            "MessageAdversaryPower": 0,
            "avgDeliveryNodes": 100.0,
            "avgDeliveryTime": 5.731958762886598,
            "byzantineNodes": [
                59,
                70,
                78
            ],
            "disconnectedNodes": [],
            "maxDeliveryTime": 6,
            "senderId": 0,
            "totalMsgsSent": 171210
        },
        "56": {
            "MessageAdversaryPower": 0,
            "avgDeliveryNodes": 100.0,
            "avgDeliveryTime": 5.731958762886598,
            "byzantineNodes": [
                59,
                70,
                78
            ],
            "disconnectedNodes": [],
            "maxDeliveryTime": 6,
            "senderId": 0,
            "totalMsgsSent": 171210
        },
        "57": {
            "MessageAdversaryPower": 0,
            "avgDeliveryNodes": 100.0,
            "avgDeliveryTime": 5.731958762886598,
            "byzantineNodes": [
                59,
                70,
                78
            ],
            "disconnectedNodes": [],
            "maxDeliveryTime": 6,
            "senderId": 0,
            "totalMsgsSent": 171210
        },
        "58": {
            "MessageAdversaryPower": 0,
            "avgDeliveryNodes": 100.0,
            "avgDeliveryTime": 5.731958762886598,
            "byzantineNodes": [
                59,
                70,
                78
            ],
            "disconnectedNodes": [],
            "maxDeliveryTime": 6,
            "senderId": 0,
            "totalMsgsSent": 171210
        },
        "59": {
            "MessageAdversaryPower": 0,
            "avgDeliveryNodes": 100.0,
            "avgDeliveryTime": 5.731958762886598,
            "byzantineNodes": [
                59,
                70,
                78
            ],
            "disconnectedNodes": [],
            "maxDeliveryTime": 6,
            "senderId": 0,
            "totalMsgsSent": 171210
        },
        "6": {
            "MessageAdversaryPower": 0,
            "avgDeliveryNodes": 100.0,
            "avgDeliveryTime": 5.731958762886598,
            "byzantineNodes": [
                59,
                70,
                78
            ],
            "disconnectedNodes": [],
            "maxDeliveryTime": 6,
            "senderId": 0,
            "totalMsgsSent": 171210
        },
        "60": {
            "MessageAdversaryPower": 0,
            "avgDeliveryNodes": 100.0,
            "avgDeliveryTime": 5.731958762886598,
            "byzantineNodes": [
                59,
                70,
                78
            ],
            "disconnectedNodes": [],
            "maxDeliveryTime": 6,
            "senderId": 0,
            "totalMsgsSent": 171210
        },
        "61": {
            "MessageAdversaryPower": 0,
            "avgDeliveryNodes": 100.0,
            "avgDeliveryTime": 5.731958762886598,
            "byzantineNodes": [
                59,
                70,
                78
            ],
            "disconnectedNodes": [],
            "maxDeliveryTime": 6,
            "senderId": 0,
            "totalMsgsSent": 171210
        },
        "62": {
            "MessageAdversaryPower": 0,
            "avgDeliveryNodes": 100.0,
            "avgDeliveryTime": 5.731958762886598,
            "byzantineNodes": [
                59,
                70,
                78
            ],
            "disconnectedNodes": [],
            "maxDeliveryTime": 6,
            "senderId": 0,
            "totalMsgsSent": 171210
        },
        "63": {
            "MessageAdversaryPower": 0,
            "avgDeliveryNodes": 100.0,
            "avgDeliveryTime": 5.731958762886598,
            "byzantineNodes": [
                59,
                70,
                78
            ],
            "disconnectedNodes": [],
            "maxDeliveryTime": 6,
            "senderId": 0,
            "totalMsgsSent": 171210
        },
        "64": {
            "MessageAdversaryPower": 0,
            "avgDeliveryNodes": 100.0,
            "avgDeliveryTime": 5.731958762886598,
            "byzantineNodes": [
                59,
                70,
                78
            ],
            "disconnectedNodes": [],
            "maxDeliveryTime": 6,
            "senderId": 0,
            "totalMsgsSent": 171210
        },
        "65": {
            "MessageAdversaryPower": 0,
            "avgDeliveryNodes": 100.0,
            "avgDeliveryTime": 5.731958762886598,
            "byzantineNodes": [
                59,
                70,
                78
            ],
            "disconnectedNodes": [],
            "maxDeliveryTime": 6,
            "senderId": 0,
            "totalMsgsSent": 171210
        },
        "66": {
            "MessageAdversaryPower": 0,
            "avgDeliveryNodes": 100.0,
            "avgDeliveryTime": 5.731958762886598,
            "byzantineNodes": [
                59,
                70,
                78
            ],
            "disconnectedNodes": [],
            "maxDeliveryTime": 6,
            "senderId": 0,
            "totalMsgsSent": 171210
        },
        "67": {
            "MessageAdversaryPower": 0,
            "avgDeliveryNodes": 100.0,
            "avgDeliveryTime": 5.731958762886598,
            "byzantineNodes": [
                59,
                70,
                78
            ],
            "disconnectedNodes": [],
            "maxDeliveryTime": 6,
            "senderId": 0,
            "totalMsgsSent": 171210
        },
        "68": {
            "MessageAdversaryPower": 0,
            "avgDeliveryNodes": 100.0,
            "avgDeliveryTime": 5.731958762886598,
            "byzantineNodes": [
                59,
                70,
                78
            ],
            "disconnectedNodes": [],
            "maxDeliveryTime": 6,
            "senderId": 0,
            "totalMsgsSent": 171210
        },
        "69": {
            "MessageAdversaryPower": 0,
            "avgDeliveryNodes": 100.0,
            "avgDeliveryTime": 5.731958762886598,
            "byzantineNodes": [
                59,
                70,
                78
            ],
            "disconnectedNodes": [],
            "maxDeliveryTime": 6,
            "senderId": 0,
            "totalMsgsSent": 171210
        },
        "7": {
            "MessageAdversaryPower": 0,
            "avgDeliveryNodes": 100.0,
            "avgDeliveryTime": 5.731958762886598,
            "byzantineNodes": [
                59,
                70,
                78
            ],
            "disconnectedNodes": [],
            "maxDeliveryTime": 6,
            "senderId": 0,
            "totalMsgsSent": 171210
        },
        "70": {
            "MessageAdversaryPower": 0,
            "avgDeliveryNodes": 100.0,
            "avgDeliveryTime": 5.731958762886598,
            "byzantineNodes": [
                59,
                70,
                78
            ],
            "disconnectedNodes": [],
            "maxDeliveryTime": 6,
            "senderId": 0,
            "totalMsgsSent": 171210
        },
        "71": {
            "MessageAdversaryPower": 0,
            "avgDeliveryNodes": 100.0,
            "avgDeliveryTime": 5.731958762886598,
            "byzantineNodes": [
                59,
                70,
                78
            ],
            "disconnectedNodes": [],
            "maxDeliveryTime": 6,
            "senderId": 0,
            "totalMsgsSent": 171210
        },
        "72": {
            "MessageAdversaryPower": 0,
            "avgDeliveryNodes": 100.0,
            "avgDeliveryTime": 5.731958762886598,
            "byzantineNodes": [
                59,
                70,
                78
            ],
            "disconnectedNodes": [],
            "maxDeliveryTime": 6,
            "senderId": 0,
            "totalMsgsSent": 171210
        },
        "73": {
            "MessageAdversaryPower": 0,
            "avgDeliveryNodes": 100.0,
            "avgDeliveryTime": 5.731958762886598,
            "byzantineNodes": [
                59,
                70,
                78
            ],
            "disconnectedNodes": [],
            "maxDeliveryTime": 6,
            "senderId": 0,
            "totalMsgsSent": 171210
        },
        "74": {
            "MessageAdversaryPower": 0,
            "avgDeliveryNodes": 100.0,
            "avgDeliveryTime": 5.731958762886598,
            "byzantineNodes": [
                59,
                70,
                78
            ],
            "disconnectedNodes": [],
            "maxDeliveryTime": 6,
            "senderId": 0,
            "totalMsgsSent": 171210
        },
        "75": {
            "MessageAdversaryPower": 0,
            "avgDeliveryNodes": 100.0,
            "avgDeliveryTime": 5.731958762886598,
            "byzantineNodes": [
                59,
                70,
                78
            ],
            "disconnectedNodes": [],
            "maxDeliveryTime": 6,
            "senderId": 0,
            "totalMsgsSent": 171210
        },
        "76": {
            "MessageAdversaryPower": 0,
            "avgDeliveryNodes": 100.0,
            "avgDeliveryTime": 5.731958762886598,
            "byzantineNodes": [
                59,
                70,
                78
            ],
            "disconnectedNodes": [],
            "maxDeliveryTime": 6,
            "senderId": 0,
            "totalMsgsSent": 171210
        },
        "77": {
            "MessageAdversaryPower": 0,
            "avgDeliveryNodes": 100.0,
            "avgDeliveryTime": 5.731958762886598,
            "byzantineNodes": [
                59,
                70,
                78
            ],
            "disconnectedNodes": [],
            "maxDeliveryTime": 6,
            "senderId": 0,
            "totalMsgsSent": 171210
        },
        "78": {
            "MessageAdversaryPower": 0,
            "avgDeliveryNodes": 100.0,
            "avgDeliveryTime": 5.731958762886598,
            "byzantineNodes": [
                59,
                70,
                78
            ],
            "disconnectedNodes": [],
            "maxDeliveryTime": 6,
            "senderId": 0,
            "totalMsgsSent": 171210
        },
        "79": {
            "MessageAdversaryPower": 0,
            "avgDeliveryNodes": 100.0,
            "avgDeliveryTime": 5.731958762886598,
            "byzantineNodes": [
                59,
                70,
                78
            ],
            "disconnectedNodes": [],
            "maxDeliveryTime": 6,
            "senderId": 0,
            "totalMsgsSent": 171210
        },
        "8": {
            "MessageAdversaryPower": 0,
            "avgDeliveryNodes": 100.0,
            "avgDeliveryTime": 5.731958762886598,
            "byzantineNodes": [
                59,
                70,
                78
            ],
            "disconnectedNodes": [],
            "maxDeliveryTime": 6,
            "senderId": 0,
            "totalMsgsSent": 171210
        },
        "80": {
            "MessageAdversaryPower": 0,
            "avgDeliveryNodes": 100.0,
            "avgDeliveryTime": 5.731958762886598,
            "byzantineNodes": [
                59,
                70,
                78
            ],
            "disconnectedNodes": [],
            "maxDeliveryTime": 6,
            "senderId": 0,
            "totalMsgsSent": 171210
        },
        "81": {
            "MessageAdversaryPower": 0,
            "avgDeliveryNodes": 100.0,
            "avgDeliveryTime": 5.731958762886598,
            "byzantineNodes": [
                59,
                70,
                78
            ],
            "disconnectedNodes": [],
            "maxDeliveryTime": 6,
            "senderId": 0,
            "totalMsgsSent": 171210
        },
        "82": {
            "MessageAdversaryPower": 0,
            "avgDeliveryNodes": 100.0,
            "avgDeliveryTime": 5.731958762886598,
            "byzantineNodes": [
                59,
                70,
                78
            ],
            "disconnectedNodes": [],
            "maxDeliveryTime": 6,
            "senderId": 0,
            "totalMsgsSent": 171210
        },
        "83": {
            "MessageAdversaryPower": 0,
            "avgDeliveryNodes": 100.0,
            "avgDeliveryTime": 5.731958762886598,
            "byzantineNodes": [
                59,
                70,
                78
            ],
            "disconnectedNodes": [],
            "maxDeliveryTime": 6,
            "senderId": 0,
            "totalMsgsSent": 171210
        },
        "84": {
            "MessageAdversaryPower": 0,
            "avgDeliveryNodes": 100.0,
            "avgDeliveryTime": 5.731958762886598,
            "byzantineNodes": [
                59,
                70,
                78
            ],
            "disconnectedNodes": [],
            "maxDeliveryTime": 6,
            "senderId": 0,
            "totalMsgsSent": 171210
        },
        "85": {
            "MessageAdversaryPower": 0,
            "avgDeliveryNodes": 100.0,
            "avgDeliveryTime": 5.731958762886598,
            "byzantineNodes": [
                59,
                70,
                78
            ],
            "disconnectedNodes": [],
            "maxDeliveryTime": 6,
            "senderId": 0,
            "totalMsgsSent": 171210
        },
        "86": {
            "MessageAdversaryPower": 0,
            "avgDeliveryNodes": 100.0,
            "avgDeliveryTime": 5.731958762886598,
            "byzantineNodes": [
                59,
                70,
                78
            ],
            "disconnectedNodes": [],
            "maxDeliveryTime": 6,
            "senderId": 0,
            "totalMsgsSent": 171210
        },
        "87": {
            "MessageAdversaryPower": 0,
            "avgDeliveryNodes": 100.0,
            "avgDeliveryTime": 5.731958762886598,
            "byzantineNodes": [
                59,
                70,
                78
            ],
            "disconnectedNodes": [],
            "maxDeliveryTime": 6,
            "senderId": 0,
            "totalMsgsSent": 171210
        },
        "88": {
            "MessageAdversaryPower": 0,
            "avgDeliveryNodes": 100.0,
            "avgDeliveryTime": 5.731958762886598,
            "byzantineNodes": [
                59,
                70,
                78
            ],
            "disconnectedNodes": [],
            "maxDeliveryTime": 6,
            "senderId": 0,
            "totalMsgsSent": 171210
        },
        "89": {
            "MessageAdversaryPower": 0,
            "avgDeliveryNodes": 100.0,
            "avgDeliveryTime": 5.731958762886598,
            "byzantineNodes": [
                59,
                70,
                78
            ],
            "disconnectedNodes": [],
            "maxDeliveryTime": 6,
            "senderId": 0,
            "totalMsgsSent": 171210
        },
        "9": {
            "MessageAdversaryPower": 0,
            "avgDeliveryNodes": 100.0,
            "avgDeliveryTime": 5.731958762886598,
            "byzantineNodes": [
                59,
                70,
                78
            ],
            "disconnectedNodes": [],
            "maxDeliveryTime": 6,
            "senderId": 0,
            "totalMsgsSent": 171210
        },
        "90": {
            "MessageAdversaryPower": 0,
            "avgDeliveryNodes": 100.0,
            "avgDeliveryTime": 5.731958762886598,
            "byzantineNodes": [
                59,
                70,
                78
            ],
            "disconnectedNodes": [],
            "maxDeliveryTime": 6,
            "senderId": 0,
            "totalMsgsSent": 171210
        },
        "91": {
            "MessageAdversaryPower": 0,
            "avgDeliveryNodes": 100.0,
            "avgDeliveryTime": 5.731958762886598,
            "byzantineNodes": [
                59,
                70,
                78
            ],
            "disconnectedNodes": [],
            "maxDeliveryTime": 6,
            "senderId": 0,
            "totalMsgsSent": 171210
        },
        "92": {
            "MessageAdversaryPower": 0,
            "avgDeliveryNodes": 100.0,
            "avgDeliveryTime": 5.731958762886598,
            "byzantineNodes": [
                59,
                70,
                78
            ],
            "disconnectedNodes": [],
            "maxDeliveryTime": 6,
            "senderId": 0,
            "totalMsgsSent": 171210
        },
        "93": {
            "MessageAdversaryPower": 0,
            "avgDeliveryNodes": 100.0,
            "avgDeliveryTime": 5.731958762886598,
            "byzantineNodes": [
                59,
                70,
                78
            ],
            "disconnectedNodes": [],
            "maxDeliveryTime": 6,
            "senderId": 0,
            "totalMsgsSent": 171210
        },
        "94": {
            "MessageAdversaryPower": 0,
            "avgDeliveryNodes": 100.0,
            "avgDeliveryTime": 5.731958762886598,
            "byzantineNodes": [
                59,
                70,
                78
            ],
            "disconnectedNodes": [],
            "maxDeliveryTime": 6,
            "senderId": 0,
            "totalMsgsSent": 171210
        },
        "95": {
            "MessageAdversaryPower": 0,
            "avgDeliveryNodes": 100.0,
            "avgDeliveryTime": 5.731958762886598,
            "byzantineNodes": [
                59,
                70,
                78
            ],
            "disconnectedNodes": [],
            "maxDeliveryTime": 6,
            "senderId": 0,
            "totalMsgsSent": 171210
        },
        "96": {
            "MessageAdversaryPower": 0,
            "avgDeliveryNodes": 100.0,
            "avgDeliveryTime": 5.731958762886598,
            "byzantineNodes": [
                59,
                70,
                78
            ],
            "disconnectedNodes": [],
            "maxDeliveryTime": 6,
            "senderId": 0,
            "totalMsgsSent": 171210
        },
        "97": {
            "MessageAdversaryPower": 0,
            "avgDeliveryNodes": 100.0,
            "avgDeliveryTime": 5.731958762886598,
            "byzantineNodes": [
                59,
                70,
                78
            ],
            "disconnectedNodes": [],
            "maxDeliveryTime": 6,
            "senderId": 0,
            "totalMsgsSent": 171210
        },
        "98": {
            "MessageAdversaryPower": 0,
            "avgDeliveryNodes": 100.0,
            "avgDeliveryTime": 5.731958762886598,
            "byzantineNodes": [
                59,
                70,
                78
            ],
            "disconnectedNodes": [],
            "maxDeliveryTime": 6,
            "senderId": 0,
            "totalMsgsSent": 171210
        },
        "99": {
            "MessageAdversaryPower": 0,
            "avgDeliveryNodes": 100.0,
            "avgDeliveryTime": 5.731958762886598,
            "byzantineNodes": [
                59,
                70,
                78
            ],
            "disconnectedNodes": [],
            "maxDeliveryTime": 6,
            "senderId": 0,
            "totalMsgsSent": 171210
        }
    }
}
