{
    "RunTime": 17.907082262,
    "tests": {
        "0": {
            "MessageAdversaryPower": 4,
            "avgDeliveryNodes": 100.0,
            "avgDeliveryTime": 5.0,
            "byzantineNodes": [],
            "disconnectedNodes": [],
            "maxDeliveryTime": 5,
            "senderId": 0,
            "totalMsgsSent": 381236
        },
        "1": {
            "MessageAdversaryPower": 4,
            "avgDeliveryNodes": 100.0,
            "avgDeliveryTime": 5.0,
            "byzantineNodes": [],
            "disconnectedNodes": [],
            "maxDeliveryTime": 5,
            "senderId": 0,
            "totalMsgsSent": 383142
        },
        "10": {
            "MessageAdversaryPower": 4,
            "avgDeliveryNodes": 100.0,
            "avgDeliveryTime": 5.0,
            "byzantineNodes": [],
            "disconnectedNodes": [],
            "maxDeliveryTime": 5,
            "senderId": 0,
            "totalMsgsSent": 383139
        },
        "11": {
            "MessageAdversaryPower": 4,
            "avgDeliveryNodes": 100.0,
            "avgDeliveryTime": 5.0,
            "byzantineNodes": [],
            "disconnectedNodes": [],
            "maxDeliveryTime": 5,
            "senderId": 0,
            "totalMsgsSent": 381251
        },
        "12": {
            "MessageAdversaryPower": 4,
            "avgDeliveryNodes": 100.0,
            "avgDeliveryTime": 5.0,
            "byzantineNodes": [],
            "disconnectedNodes": [],
            "maxDeliveryTime": 5,
            "senderId": 0,
            "totalMsgsSent": 383139
        },
        "13": {
            "MessageAdversaryPower": 4,
            "avgDeliveryNodes": 100.0,
            "avgDeliveryTime": 5.0,
            "byzantineNodes": [],
            "disconnectedNodes": [],
            "maxDeliveryTime": 5,
            "senderId": 0,
            "totalMsgsSent": 381245
        },
        "14": {
            "MessageAdversaryPower": 4,
            "avgDeliveryNodes": 100.0,
            "avgDeliveryTime": 5.0,
            "byzantineNodes": [],
            "disconnectedNodes": [],
            "maxDeliveryTime": 5,
            "senderId": 0,
            "totalMsgsSent": 383147
        },
        "15": {
            "MessageAdversaryPower": 4,
            "avgDeliveryNodes": 100.0,
            "avgDeliveryTime": 5.0,
            "byzantineNodes": [],
            "disconnectedNodes": [],
            "maxDeliveryTime": 5,
            "senderId": 0,
            "totalMsgsSent": 381245
        },
        "16": {
            "MessageAdversaryPower": 4,
            "avgDeliveryNodes": 100.0,
            "avgDeliveryTime": 5.0,
            "byzantineNodes": [],
            "disconnectedNodes": [],
            "maxDeliveryTime": 5,
            "senderId": 0,
            "totalMsgsSent": 381241
        },
        "17": {
            "MessageAdversaryPower": 4,
            "avgDeliveryNodes": 100.0,
            "avgDeliveryTime": 5.0,
            "byzantineNodes": [],
            "disconnectedNodes": [],
            "maxDeliveryTime": 5,
            "senderId": 0,
            "totalMsgsSent": 383142
        },
        "18": {
            "MessageAdversaryPower": 4,
            "avgDeliveryNodes": 100.0,
            "avgDeliveryTime": 5.0,
            "byzantineNodes": [],
            "disconnectedNodes": [],
            "maxDeliveryTime": 5,
            "senderId": 0,
            "totalMsgsSent": 383159
        },
        "19": {
            "MessageAdversaryPower": 4,
            "avgDeliveryNodes": 100.0,
            "avgDeliveryTime": 5.0,
            "byzantineNodes": [],
            "disconnectedNodes": [],
            "maxDeliveryTime": 5,
            "senderId": 0,
            "totalMsgsSent": 381242
        },
        "2": {
            "MessageAdversaryPower": 4,
            "avgDeliveryNodes": 100.0,
            "avgDeliveryTime": 5.0,
            "byzantineNodes": [],
            "disconnectedNodes": [],
            "maxDeliveryTime": 5,
            "senderId": 0,
            "totalMsgsSent": 383144
        },
        "20": {
            "MessageAdversaryPower": 4,
            "avgDeliveryNodes": 100.0,
            "avgDeliveryTime": 5.0,
            "byzantineNodes": [],
            "disconnectedNodes": [],
            "maxDeliveryTime": 5,
            "senderId": 0,
            "totalMsgsSent": 381236
        },
        "21": {
            "MessageAdversaryPower": 4,
            "avgDeliveryNodes": 100.0,
            "avgDeliveryTime": 5.0,
            "byzantineNodes": [],
            "disconnectedNodes": [],
            "maxDeliveryTime": 5,
            "senderId": 0,
            "totalMsgsSent": 383160
        },
        "22": {
            "MessageAdversaryPower": 4,
            "avgDeliveryNodes": 100.0,
            "avgDeliveryTime": 5.0,
            "byzantineNodes": [],
            "disconnectedNodes": [],
            "maxDeliveryTime": 5,
            "senderId": 0,
            "totalMsgsSent": 383153
        },
        "23": {
            "MessageAdversaryPower": 4,
            "avgDeliveryNodes": 100.0,
            "avgDeliveryTime": 5.0,
            "byzantineNodes": [],
            "disconnectedNodes": [],
            "maxDeliveryTime": 5,
            "senderId": 0,
            "totalMsgsSent": 383152
        },
        "24": {
            "MessageAdversaryPower": 4,
            "avgDeliveryNodes": 100.0,
            "avgDeliveryTime": 5.0,
            "byzantineNodes": [],
            "disconnectedNodes": [],
            "maxDeliveryTime": 5,
            "senderId": 0,
            "totalMsgsSent": 383148
        },
        "3": {
            "MessageAdversaryPower": 4,
            "avgDeliveryNodes": 100.0,
            "avgDeliveryTime": 5.0,
            "byzantineNodes": [],
            "disconnectedNodes": [],
            "maxDeliveryTime": 5,
            "senderId": 0,
            "totalMsgsSent": 383143
        },
        "4": {
            "MessageAdversaryPower": 4,
            "avgDeliveryNodes": 100.0,
            "avgDeliveryTime": 5.0,
            "byzantineNodes": [],
            "disconnectedNodes": [],
            "maxDeliveryTime": 5,
            "senderId": 0,
            "totalMsgsSent": 381243
        },
        "5": {
            "MessageAdversaryPower": 4,
            "avgDeliveryNodes": 100.0,
            "avgDeliveryTime": 5.0,
            "byzantineNodes": [],
            "disconnectedNodes": [],
            "maxDeliveryTime": 5,
            "senderId": 0,
            "totalMsgsSent": 383146
        },
        "6": {
            "MessageAdversaryPower": 4,
            "avgDeliveryNodes": 100.0,
            "avgDeliveryTime": 5.0,
            "byzantineNodes": [],
            "disconnectedNodes": [],
            "maxDeliveryTime": 5,
            "senderId": 0,
            "totalMsgsSent": 383139
        },
        "7": {
            "MessageAdversaryPower": 4,
            "avgDeliveryNodes": 100.0,
            "avgDeliveryTime": 5.0,
            "byzantineNodes": [],
            "disconnectedNodes": [],
            "maxDeliveryTime": 5,
            "senderId": 0,
            "totalMsgsSent": 381246
        },
        "8": {
            "MessageAdversaryPower": 4,
            "avgDeliveryNodes": 100.0,
            "avgDeliveryTime": 5.0,
            "byzantineNodes": [],
            "disconnectedNodes": [],
            "maxDeliveryTime": 5,
            "senderId": 0,
            "totalMsgsSent": 383145
        },
        "9": {
            "MessageAdversaryPower": 4,
            "avgDeliveryNodes": 100.0,
            "avgDeliveryTime": 5.0,
            "byzantineNodes": [],
            "disconnectedNodes": [],
            "maxDeliveryTime": 5,
            "senderId": 0,
            "totalMsgsSent": 383156
        }
    }
}
